exit_pipe/__init__.py
exit_pipe-1.0.0.dist-info/LICENSE
exit_pipe-1.0.0.dist-info/METADATA
exit_pipe-1.0.0.dist-info/WHEEL
exit_pipe-1.0.0.dist-info/entry_points.txt
exit_pipe-1.0.0.dist-info/top_level.txt
exit_pipe-1.0.0.dist-info/RECORD
