Metadata-Version: 2.1
Name: exit-pipe
Version: 1.0.0
Summary: a command-line utility to pipe the exit code from a subprocess through one or more modifiers
Home-page: https://github.com/jwilges/exit-pipe
Author: Jeffrey Wilges
Author-email: jeffrey@wilges.com
License: BSD
Platform: UNKNOWN
Classifier: Development Status :: 4 - Beta
Classifier: Environment :: Console
Classifier: License :: OSI Approved :: BSD License
Classifier: Operating System :: MacOS :: MacOS X
Classifier: Operating System :: Microsoft :: Windows
Classifier: Operating System :: POSIX
Classifier: Programming Language :: Python :: 3
Classifier: Topic :: Utilities
Requires-Python: >=3.6
